alawymdb-0.2.27.dist-info/METADATA
alawymdb-0.2.27.dist-info/WHEEL
alawymdb/__init__.py
alawymdb/alawymdb.cpython-311-x86_64-linux-gnu.so
alawymdb-0.2.27.dist-info/RECORD
