Metadata-Version: 2.4
Name: alawymdb
Version: 0.2.27
Classifier: Development Status :: 3 - Alpha
Classifier: Intended Audience :: Developers
Classifier: Programming Language :: Python :: 3
Classifier: Programming Language :: Python :: 3.7
Classifier: Programming Language :: Python :: 3.8
Classifier: Programming Language :: Python :: 3.9
Classifier: Programming Language :: Python :: 3.10
Classifier: Programming Language :: Python :: 3.11
Classifier: Programming Language :: Python :: 3.12
Classifier: Programming Language :: Rust
Classifier: Topic :: Database
Classifier: Operating System :: OS Independent
Requires-Dist: numpy>=1.20.0
Requires-Dist: pandas>=1.3.0
Summary: Linear-scaling in-memory database optimized for ML workloads
Keywords: database,columnar,in-memory,performance
Author-email: Tomio Kobayashi <tomkob99@yahoo.co.jp>
License: MIT
Requires-Python: >=3.7
